n4e_pyadv25_tool/main.py
n4e_pyadv25_tool-0.3.0.dist-info/METADATA
n4e_pyadv25_tool-0.3.0.dist-info/WHEEL
n4e_pyadv25_tool-0.3.0.dist-info/RECORD
